fairchem/data/oc/.flake8
fairchem/data/oc/LICENSE.md
fairchem/data/oc/README.md
fairchem/data/oc/README_legacy_OC20.md
fairchem/data/oc/__init__.py
fairchem/data/oc/codecov.yml
fairchem/data/oc/ocdata_workflow.png
fairchem/data/oc/structure_generator.py
fairchem/data/oc/workflow_image.png
fairchem/data/oc/core/__init__.py
fairchem/data/oc/core/adsorbate.py
fairchem/data/oc/core/adsorbate_slab_config.py
fairchem/data/oc/core/bulk.py
fairchem/data/oc/core/interface_config.py
fairchem/data/oc/core/ion.py
fairchem/data/oc/core/multi_adsorbate_slab_config.py
fairchem/data/oc/core/slab.py
fairchem/data/oc/core/solvent.py
fairchem/data/oc/databases/__init__.py
fairchem/data/oc/databases/update.py
fairchem/data/oc/databases/pkls/__init__.py
fairchem/data/oc/databases/pkls/adsorbates.pkl
fairchem/data/oc/databases/pkls/ions.pkl
fairchem/data/oc/databases/pkls/solvents.pkl
fairchem/data/oc/scripts/precompute_sample_structures.py
fairchem/data/oc/utils/__init__.py
fairchem/data/oc/utils/flag_anomaly.py
fairchem/data/oc/utils/geometry.py
fairchem/data/oc/utils/vasp.py
fairchem/data/oc/utils/vasp_flags.py
fairchem_data_oc-1.0.2.dist-info/METADATA
fairchem_data_oc-1.0.2.dist-info/WHEEL
fairchem_data_oc-1.0.2.dist-info/RECORD
