Metadata-Version: 2.4
Name: fairchem-data-oc
Version: 1.0.2
Summary: Code for generating adsorbate-catalyst input configurations
Project-URL: repository, https://github.com/facebookresearch/fairchem/tree/main/src/fairchem/data/oc
Project-URL: documentation, https://fair-chem.github.io/
License: MIT License
Requires-Dist: ase
Requires-Dist: matplotlib
Requires-Dist: numpy
Requires-Dist: pymatgen>=2023.10.3
Requires-Dist: scipy
Requires-Dist: tqdm
